camels_attrs/__init__.py
camels_attrs/cli.py
camels_attrs/climate.py
camels_attrs/extractor.py
camels_attrs/geology.py
camels_attrs/hydrology.py
camels_attrs/multi_gauge_viz.py
camels_attrs/soil.py
camels_attrs/timeseries.py
camels_attrs/topography.py
camels_attrs/vegetation.py
camels_attrs/visualization.py
camels_attrs/watershed.py
camels_attrs-1.0.2.dist-info/licenses/LICENSE
camels_attrs-1.0.2.dist-info/METADATA
camels_attrs-1.0.2.dist-info/WHEEL
camels_attrs-1.0.2.dist-info/entry_points.txt
camels_attrs-1.0.2.dist-info/top_level.txt
camels_attrs-1.0.2.dist-info/RECORD
