Metadata-Version: 2.4
Name: camels-attrs
Version: 1.0.2
Summary: Extract CAMELS-like catchment attributes for any USGS gauge site in the USA
Author-email: Mohammad Galib <mgalib@purdue.edu>
Maintainer-email: Mohammad Galib <mgalib@purdue.edu>
License: MIT
Project-URL: Homepage, https://github.com/galib9690/camels-attrs
Project-URL: Documentation, https://github.com/galib9690/camels-attrs#readme
Project-URL: Repository, https://github.com/galib9690/camels-attrs
Project-URL: Issues, https://github.com/galib9690/camels-attrs/issues
Keywords: hydrology,CAMELS,catchment,watershed,USGS,attributes
Classifier: Development Status :: 4 - Beta
Classifier: Intended Audience :: Science/Research
Classifier: Topic :: Scientific/Engineering :: Hydrology
Classifier: License :: OSI Approved :: MIT License
Classifier: Programming Language :: Python :: 3
Classifier: Programming Language :: Python :: 3.8
Classifier: Programming Language :: Python :: 3.9
Classifier: Programming Language :: Python :: 3.10
Classifier: Programming Language :: Python :: 3.11
Requires-Python: >=3.10
License-File: LICENSE
Requires-Dist: numpy>=1.20.0
Requires-Dist: pandas>=1.3.0
Requires-Dist: geopandas>=0.10.0
Requires-Dist: xarray>=0.19.0
Requires-Dist: rioxarray>=0.11.0
Requires-Dist: rasterio>=1.2.0
Requires-Dist: shapely>=1.8.0
Requires-Dist: pynhd>=0.14.0
Requires-Dist: py3dep>=0.14.0
Requires-Dist: xarray-spatial>=0.3.0
Requires-Dist: pygridmet>=0.14.0
Requires-Dist: pygeohydro>=0.14.0
Requires-Dist: pygeoutils>=0.14.0
Requires-Dist: pystac-client>=0.5.0
Requires-Dist: planetary-computer>=0.4.0
Requires-Dist: scipy>=1.7.0
Requires-Dist: hydrofunctions>=0.2.0
Requires-Dist: matplotlib>=3.4.0
Requires-Dist: requests>=2.25.0
Requires-Dist: contextily>=1.2.0
Requires-Dist: cartopy>=0.20.0
Requires-Dist: earthengine-api
Requires-Dist: pygeoglim>=1.0.5
Requires-Dist: dask>=2021.0.0
Provides-Extra: dev
Requires-Dist: pytest>=7.0.0; extra == "dev"
Requires-Dist: pytest-cov>=3.0.0; extra == "dev"
Requires-Dist: black>=22.0.0; extra == "dev"
Requires-Dist: flake8>=4.0.0; extra == "dev"
Requires-Dist: mypy>=0.950; extra == "dev"
Dynamic: license-file
